payload/__init__.py
payload/arm/__init__.py
payload/arm/attr.py
payload/arm/object.py
payload/arm/request.py
payload/arm/session.py
payload/exceptions.py
payload/objects.py
payload/utils.py
payload/version.py
payload_api-0.5.0.dist-info/WHEEL
payload_api-0.5.0.dist-info/METADATA
payload_api-0.5.0.dist-info/licenses/LICENSE
payload_api-0.5.0.dist-info/RECORD
