Metadata-Version: 2.1
Name: payload-api
Version: 0.5.0
Summary: Payload Python Library
License: MIT
Author-email: Payload <help@payload.com>
Requires-Python: >=3.7
Requires-Dist: importlib-metadata
Requires-Dist: requests
Requires-Dist: six
Requires-Dist: urllib3>=1.26.5
Project-URL: Documentation, https://docs.payload.com
Project-URL: Homepage, https://payload.com
Project-URL: Repository, https://github.com/payload-code/payload-python
